{
  "lastBuildDate": "Mon, 27 Apr 2026 15:10:52 +0900",
  "total": 5,
  "start": 1,
  "display": 5,
  "items": [
    {
      "title": "모던김밥",
      "link": "",
      "category": "분식>김밥",
      "description": "",
      "telephone": "",
      "address": "서울특별시 종로구 적선동 97",
      "roadAddress": "서울특별시 종로구 자하문로2길 10",
      "mapx": "1269731772",
      "mapy": "375764902"
    },
    {
      "title": "본김밥",
      "link": "",
      "category": "분식>김밥",
      "description": "",
      "telephone": "",
      "address": "서울특별시 종로구 사직동 9 광화문 풍림스페이스본",
      "roadAddress": "서울특별시 종로구 사직로8길 4 광화문 풍림스페이스본",
      "mapx": "1269699607",
      "mapy": "375746116"
    },
    {
      "title": "명가김밥",
      "link": "",
      "category": "분식>김밥",
      "description": "",
      "telephone": "",
      "address": "서울특별시 종로구 적선동 80 적선현대빌딩 아케이드 17호",
      "roadAddress": "서울특별시 종로구 사직로 130 적선현대빌딩 아케이드 17호",
      "mapx": "1269732696",
      "mapy": "375753675"
    },
    {
      "title": "소담",
      "link": "",
      "category": "분식>종합분식",
      "description": "",
      "telephone": "",
      "address": "서울특별시 종로구 적선동 80 적선현대빌딩",
      "roadAddress": "서울특별시 종로구 사직로 130 적선현대빌딩",
      "mapx": "1269732383",
      "mapy": "375753957"
    },
    {
      "title": "토스토리 서울적선1호점",
      "link": "https://blog.naver.com/toastory_1",
      "category": "분식>토스트",
      "description": "",
      "telephone": "",
      "address": "서울특별시 종로구 적선동 80 지하1층 아케이드 59호",
      "roadAddress": "서울특별시 종로구 사직로 130 지하1층 아케이드 59호",
      "mapx": "1269733436",
      "mapy": "375753767"
    }
  ]
}