{
  "lastBuildDate": "Sun, 08 Mar 2026 21:51:42 +0900",
  "total": 5,
  "start": 1,
  "display": 5,
  "items": [
    {
      "title": "황생가칼국수",
      "link": "http://황생가칼국수.com",
      "category": "한식>칼국수,만두",
      "description": "",
      "telephone": "",
      "address": "서울특별시 종로구 소격동 84",
      "roadAddress": "서울특별시 종로구 북촌로5길 78",
      "mapx": "1269806900",
      "mapy": "375801317"
    },
    {
      "title": "사직로 서울",
      "link": "https://www.instagram.com/sajikro_seoul",
      "category": "음식점>한식",
      "description": "",
      "telephone": "",
      "address": "서울특별시 종로구 적선동 94 2층",
      "roadAddress": "서울특별시 종로구 사직로 127-14 2층",
      "mapx": "1269730650",
      "mapy": "375761905"
    },
    {
      "title": "도량",
      "link": "https://app.catchtable.co.kr/ct/shop/dolyang?from=share&type=WAITING://",
      "category": "중식>중식당",
      "description": "",
      "telephone": "",
      "address": "서울특별시 종로구 통의동 35-12 2, 3층",
      "roadAddress": "서울특별시 종로구 자하문로6길 6 2, 3층",
      "mapx": "1269724921",
      "mapy": "375780066"
    },
    {
      "title": "대선칼국수",
      "link": "",
      "category": "한식>칼국수,만두",
      "description": "",
      "telephone": "",
      "address": "서울특별시 종로구 통의동 35-42 우진빌딩 2층 대선칼국수",
      "roadAddress": "서울특별시 종로구 자하문로4길 6 우진빌딩 2층 대선칼국수",
      "mapx": "1269726245",
      "mapy": "375771878"
    },
    {
      "title": "잘빠진메밀 서촌 본점",
      "link": "https://smartstore.naver.com/jalppajin-mill",
      "category": "한식>막국수",
      "description": "",
      "telephone": "",
      "address": "서울특별시 종로구 통인동 120",
      "roadAddress": "서울특별시 종로구 자하문로11길 4",
      "mapx": "1269709994",
      "mapy": "375796715"
    }
  ]
}