{
  "lastBuildDate": "Mon, 09 Mar 2026 11:33:22 +0900",
  "total": 5,
  "start": 1,
  "display": 5,
  "items": [
    {
      "title": "오공김밥 한성대입구역점",
      "link": "",
      "category": "음식점>분식",
      "description": "",
      "telephone": "",
      "address": "서울특별시 성북구 동소문동1가 29 1층",
      "roadAddress": "서울특별시 성북구 동소문로 9-2 1층",
      "mapx": "1270072738",
      "mapy": "375891516"
    },
    {
      "title": "호랑이김밥",
      "link": "",
      "category": "분식>김밥",
      "description": "",
      "telephone": "",
      "address": "서울특별시 성북구 성북동 184-90",
      "roadAddress": "서울특별시 성북구 성북로 18",
      "mapx": "1270049377",
      "mapy": "375897973"
    },
    {
      "title": "삼동소바 <b>성북동</b>점",
      "link": "https://samdongsoba.com",
      "category": "음식점>일식>우동,소바",
      "description": "",
      "telephone": "",
      "address": "서울특별시 성북구 성북동 243-12 1층 삼동소바 점",
      "roadAddress": "서울특별시 성북구 성북로 121 1층 삼동소바 성북동점",
      "mapx": "1269956728",
      "mapy": "375937434"
    },
    {
      "title": "송혜자김밥",
      "link": "",
      "category": "분식>김밥",
      "description": "",
      "telephone": "",
      "address": "서울특별시 성북구 동소문동4가 220",
      "roadAddress": "서울특별시 성북구 동소문로3길 149",
      "mapx": "1270123565",
      "mapy": "375925456"
    },
    {
      "title": "중경당",
      "link": "http://instagram.com/mothersfood_cooking_class/",
      "category": "음식점>한식",
      "description": "",
      "telephone": "",
      "address": "서울특별시 성북구 성북동1가 87 1층 중경당",
      "roadAddress": "서울특별시 성북구 창경궁로43길 30 1층 중경당",
      "mapx": "1270040726",
      "mapy": "375893443"
    }
  ]
}