{
  "lastBuildDate": "Mon, 09 Mar 2026 11:33:54 +0900",
  "total": 5,
  "start": 1,
  "display": 5,
  "items": [
    {
      "title": "육미안 혜화점",
      "link": "https://app.catchtable.co.kr/ct/shop/yookmian",
      "category": "한식>소고기구이",
      "description": "",
      "telephone": "",
      "address": "서울특별시 종로구 명륜2가 182-1 1층 육미안",
      "roadAddress": "서울특별시 종로구 창경궁로 246-4 1층 육미안",
      "mapx": "1269993945",
      "mapy": "375832566"
    },
    {
      "title": "삼안<b>갈비</b>촌",
      "link": "",
      "category": "한식>육류,고기요리",
      "description": "",
      "telephone": "",
      "address": "서울특별시 종로구 명륜4가 16-1 1층",
      "roadAddress": "서울특별시 종로구 대명1길 7 1층",
      "mapx": "1270010118",
      "mapy": "375831396"
    },
    {
      "title": "유캔하이 혜화역점",
      "link": "https://www.instagram.com/youcanhigh_hyehwa",
      "category": "한식>소고기구이",
      "description": "",
      "telephone": "",
      "address": "서울특별시 종로구 명륜2가 177 1층",
      "roadAddress": "서울특별시 종로구 창경궁로 246-3 1층",
      "mapx": "1269997111",
      "mapy": "375833720"
    },
    {
      "title": "동숭숯불<b>갈비</b>",
      "link": "",
      "category": "한식>육류,고기요리",
      "description": "",
      "telephone": "",
      "address": "서울특별시 종로구 명륜4가 118-8",
      "roadAddress": "서울특별시 종로구 대학로9길 26",
      "mapx": "1270005992",
      "mapy": "375816895"
    },
    {
      "title": "고봉당 혜화대학로본점",
      "link": "https://www.instagram.com/gobongdang",
      "category": "음식점>한식",
      "description": "",
      "telephone": "",
      "address": "서울특별시 종로구 명륜4가 11-3 1층 고봉당 혜화대학로점",
      "roadAddress": "서울특별시 종로구 대명1길 8 1층 고봉당 혜화대학로점",
      "mapx": "1270007774",
      "mapy": "375832052"
    }
  ]
}