{
  "lastBuildDate": "Mon, 27 Apr 2026 15:18:48 +0900",
  "total": 5,
  "start": 1,
  "display": 5,
  "items": [
    {
      "title": "애즈라이크 서촌",
      "link": "http://www.instagram.com/aslike_",
      "category": "음식점>브런치",
      "description": "",
      "telephone": "",
      "address": "서울특별시 종로구 통의동 7-33 1층 애즈라이크",
      "roadAddress": "서울특별시 종로구 효자로7길 23 1층 애즈라이크",
      "mapx": "1269733577",
      "mapy": "375783143"
    },
    {
      "title": "H라운지",
      "link": "https://m.site.naver.com/1DVXM",
      "category": "음식점>양식",
      "description": "",
      "telephone": "",
      "address": "서울특별시 종로구 통의동 35-21",
      "roadAddress": "서울특별시 종로구 자하문로4길 21-9",
      "mapx": "1269735061",
      "mapy": "375779155"
    },
    {
      "title": "보사우러스 광화문",
      "link": "https://pf.kakao.com/_dxkxjhs",
      "category": "음식점>브런치",
      "description": "",
      "telephone": "",
      "address": "서울특별시 종로구 내수동 167 대우빌딩 복합동1층",
      "roadAddress": "서울특별시 종로구 새문안로3길 30 대우빌딩 복합동1층",
      "mapx": "1269731412",
      "mapy": "375728043"
    },
    {
      "title": "쁘띠통",
      "link": "https://smartstore.naver.com/petittong",
      "category": "음식점>카페,디저트",
      "description": "",
      "telephone": "",
      "address": "서울특별시 종로구 통의동 25-16 쁘띠통",
      "roadAddress": "서울특별시 종로구 자하문로6길 11-9 쁘띠통",
      "mapx": "1269726116",
      "mapy": "375785701"
    },
    {
      "title": "아이엠베이글 광화문점",
      "link": "https://blog.naver.com/kyundotcom",
      "category": "음식점>브런치",
      "description": "",
      "telephone": "",
      "address": "서울특별시 종로구 내수동 110-48 1층",
      "roadAddress": "서울특별시 종로구 경희궁2길 7 1층",
      "mapx": "1269709765",
      "mapy": "375728521"
    }
  ]
}