{
  "lastBuildDate": "Mon, 09 Mar 2026 15:36:58 +0900",
  "total": 5,
  "start": 1,
  "display": 5,
  "items": [
    {
      "title": "어반플랜트 합정",
      "link": "http://www.instagram.com/urbanplant_official/",
      "category": "브런치카페",
      "description": "",
      "telephone": "",
      "address": "서울특별시 마포구 합정동 360-3 어반플랜트 합정",
      "roadAddress": "서울특별시 마포구 독막로6길 35 어반플랜트 합정",
      "mapx": "1269170914",
      "mapy": "375464712"
    },
    {
      "title": "히포 <b>브런치</b>하우스",
      "link": "https://www.instagram.com/brunchhaus_hippo/",
      "category": "음식점>카페,디저트",
      "description": "",
      "telephone": "",
      "address": "서울특별시 마포구 연남동 487-34 1층",
      "roadAddress": "서울특별시 마포구 성미산로17길 85 1층",
      "mapx": "1269172618",
      "mapy": "375652288"
    },
    {
      "title": "잼잼",
      "link": "https://www.instagram.com/jamjam.cafe/",
      "category": "음식점>카페,디저트",
      "description": "",
      "telephone": "",
      "address": "서울특별시 마포구 연남동 241-31 지하1층",
      "roadAddress": "서울특별시 마포구 성미산로29길 24 지하1층",
      "mapx": "1269223616",
      "mapy": "375650550"
    },
    {
      "title": "해옫 합정",
      "link": "https://blog.naver.com/heod_d",
      "category": "음식점>양식",
      "description": "",
      "telephone": "",
      "address": "서울특별시 마포구 합정동 360-17 1층",
      "roadAddress": "서울특별시 마포구 독막로8길 30 1층",
      "mapx": "1269176238",
      "mapy": "375466160"
    },
    {
      "title": "오뗄드꾸뜨",
      "link": "https://www.instagram.com/hotel_de_ggoodd?igsh=ODA1NTc5OTg5Nw==",
      "category": "음식점>양식",
      "description": "",
      "telephone": "",
      "address": "서울특별시 마포구 연남동 387-19 101호 1.5층",
      "roadAddress": "서울특별시 마포구 동교로46길 7 101호 1.5층",
      "mapx": "1269253227",
      "mapy": "375627102"
    }
  ]
}