{
  "lastBuildDate": "Mon, 09 Mar 2026 15:39:19 +0900",
  "total": 5,
  "start": 1,
  "display": 5,
  "items": [
    {
      "title": "야래향",
      "link": "",
      "category": "중식>중식당",
      "description": "",
      "telephone": "",
      "address": "서울특별시 중구 회현동1가 92-16",
      "roadAddress": "서울특별시 중구 퇴계로10길 14",
      "mapx": "1269801500",
      "mapy": "375587083"
    },
    {
      "title": "홍복",
      "link": "",
      "category": "중식>중식당",
      "description": "",
      "telephone": "",
      "address": "서울특별시 중구 회현동1가 202-5 일신빌딩 1층 - 5층",
      "roadAddress": "서울특별시 중구 남대문시장길 73-3 일신빌딩 1층 - 5층",
      "mapx": "1269800814",
      "mapy": "375609820"
    },
    {
      "title": "더퍼스트 서래향 시청점",
      "link": "https://www.instagram.com/verefood_official",
      "category": "중식>중식당",
      "description": "",
      "telephone": "",
      "address": "서울특별시 중구 남대문로3가 94 1층 101호, 102호, 103호, 104호",
      "roadAddress": "서울특별시 중구 남대문로 27 1층 101호, 102호, 103호, 104호",
      "mapx": "1269785594",
      "mapy": "375613479"
    },
    {
      "title": "행화촌",
      "link": "http://henghwachon.cityfood.co.kr/",
      "category": "중식>중식당",
      "description": "",
      "telephone": "",
      "address": "서울특별시 중구 명동2가 107-1",
      "roadAddress": "서울특별시 중구 남대문로 52-5",
      "mapx": "1269817245",
      "mapy": "375621053"
    },
    {
      "title": "자매식당",
      "link": "",
      "category": "중식>중식당",
      "description": "",
      "telephone": "",
      "address": "서울특별시 중구 남창동 50-23 2층",
      "roadAddress": "서울특별시 중구 남대문시장2가길 6-9 2층",
      "mapx": "1269769660",
      "mapy": "375592263"
    }
  ]
}